mlib.py
mlib_nsi-1.1.2.dist-info/LICENSE.txt
mlib_nsi-1.1.2.dist-info/METADATA
mlib_nsi-1.1.2.dist-info/WHEEL
mlib_nsi-1.1.2.dist-info/top_level.txt
mlib_nsi-1.1.2.dist-info/RECORD
