Metadata-Version: 2.1
Name: mlib-nsi
Version: 1.1.2
Summary: MLib is a little python library make by a 12 degrees french students
Author-email: Matt_o <mmattmmo@gmail.com>
License: MIT License
Project-URL: Homepage, https://matto.glitch.me/?mlib=go
Keywords: mlib,mgui,nsi,premiere,lycee
Classifier: License :: OSI Approved :: MIT License
Classifier: Programming Language :: Python
Classifier: Programming Language :: Python :: 3
Requires-Python: >=3.7
License-File: LICENSE.txt
Requires-Dist: pygame
Requires-Dist: Pillow
Requires-Dist: pyperclip
